{
	"name": "NOITE_DE_JOGOS",
	"plugin-id": "Sprite",
	"sid": 685331808767027,
	"isGlobal": false,
	"instanceVariables": [],
	"behaviorTypes": [],
	"effectTypes": [],
	"animations": {
		"items": [
			{
				"frames": [
					{
						"width": 150,
						"height": 50,
						"originX": 0.5,
						"originY": 0.5,
						"originalSource": "",
						"exportFormat": "png",
						"exportQuality": 0.8,
						"imageSpriteId": 3950327,
						"useCollisionPoly": true,
						"duration": 1
					}
				],
				"sid": 464205108147023,
				"name": "Default",
				"isLooping": false,
				"isPingPong": false,
				"repeatCount": 1,
				"repeatTo": 0,
				"speed": 5
			}
		],
		"subfolders": []
	}
}